genreq/__init__.py
genreq/cli.py
genreq/genreq.py
genreq/requirements.txt
genreq-1.1.0.dist-info/licenses/AUTHORS.rst
genreq-1.1.0.dist-info/licenses/LICENSE
genreq-1.1.0.dist-info/METADATA
genreq-1.1.0.dist-info/WHEEL
genreq-1.1.0.dist-info/entry_points.txt
genreq-1.1.0.dist-info/top_level.txt
genreq-1.1.0.dist-info/RECORD
