Metadata-Version: 2.4
Name: genreq
Version: 1.1.0
Summary: A Python tool that automatically detects python packages used in a project and generate a requirements.txt file
Author-email: Ziad Elshahawy <zelshahawy@uchicago.edu>
Maintainer-email: Ziad Elshahawy <zelshahawy@uchicago.edu>
License: BSD license
Project-URL: bugs, https://github.com/zelshahawy/genreq/issues
Project-URL: changelog, https://github.com/zelshahawy/genreq/blob/master/changelog.md
Project-URL: homepage, https://github.com/zelshahawy/genreq
License-File: LICENSE
License-File: AUTHORS.rst
Provides-Extra: dev
Requires-Dist: coverage; extra == "dev"
Requires-Dist: mypy; extra == "dev"
Requires-Dist: pytest; extra == "dev"
Requires-Dist: ruff; extra == "dev"
Dynamic: license-file
